__init__.py
cli.py
maintsight_pip-0.4.0.dist-info/licenses/LICENSE
models/__init__.py
models/commit_data.py
models/file_stats.py
models/risk_category.py
models/risk_prediction.py
models/xgboost_model.pkl
models/xgboost_model.py
models/xgboost_model_metadata.json
services/__init__.py
services/feature_engineer.py
services/git_commit_collector.py
services/git_feature_extractor.py
services/post_processor.py
services/temporal_data_generator.py
services/xgboost_predictor.py
utils/__init__.py
utils/html_generator.py
utils/logger.py
maintsight_pip-0.4.0.dist-info/METADATA
maintsight_pip-0.4.0.dist-info/WHEEL
maintsight_pip-0.4.0.dist-info/entry_points.txt
maintsight_pip-0.4.0.dist-info/top_level.txt
maintsight_pip-0.4.0.dist-info/RECORD
