Metadata-Version: 2.4
Name: maintsight-pip
Version: 0.4.0
Summary: AI-powered maintenance risk predictor for git repositories using XGBoost
Home-page: https://github.com/techdebtgpt/maintsight
Author: TechDebtGPT Team
Author-email: TechDebtGPT Team <support@techdebtgpt.com>
Maintainer-email: TechDebtGPT Team <support@techdebtgpt.com>
License: Apache-2.0
Project-URL: Homepage, https://github.com/floristafa/maintsight-pip
Project-URL: Documentation, https://github.com/floristafa/maintsight-pip#readme
Project-URL: Repository, https://github.com/floristafa/maintsight-pip
Project-URL: Bug Tracker, https://github.com/floristafa/maintsight-pip/issues
Keywords: maintenance,technical-debt,risk-prediction,xgboost,git,code-quality,machine-learning,repository-health
Classifier: Development Status :: 4 - Beta
Classifier: Intended Audience :: Developers
Classifier: License :: OSI Approved :: Apache Software License
Classifier: Operating System :: OS Independent
Classifier: Programming Language :: Python :: 3
Classifier: Programming Language :: Python :: 3.8
Classifier: Programming Language :: Python :: 3.9
Classifier: Programming Language :: Python :: 3.10
Classifier: Programming Language :: Python :: 3.11
Classifier: Programming Language :: Python :: 3.12
Classifier: Topic :: Software Development :: Quality Assurance
Classifier: Topic :: Software Development :: Version Control :: Git
Classifier: Topic :: Scientific/Engineering :: Artificial Intelligence
Requires-Python: >=3.8
License-File: LICENSE
Requires-Dist: click>=8.0.0
Requires-Dist: dill>=0.3.6
Requires-Dist: gitpython>=3.1.0
Requires-Dist: joblib>=1.3.0
Requires-Dist: numpy>=1.21.0
Requires-Dist: pandas>=1.3.0
Requires-Dist: scikit-learn>=1.1.0
Requires-Dist: xgboost>=1.6.0
Requires-Dist: jinja2>=3.0.0
Requires-Dist: rich>=12.0.0
Requires-Dist: tqdm>=4.62.0
Requires-Dist: typing-extensions>=4.0.0; python_version < "3.10"
Provides-Extra: dev
Requires-Dist: pytest>=6.0.0; extra == "dev"
Requires-Dist: pytest-cov>=2.12.0; extra == "dev"
Requires-Dist: black>=22.0.0; extra == "dev"
Requires-Dist: isort>=5.10.0; extra == "dev"
Requires-Dist: flake8>=4.0.0; extra == "dev"
Requires-Dist: mypy>=0.950; extra == "dev"
Requires-Dist: pre-commit>=2.15.0; extra == "dev"
Provides-Extra: html
Requires-Dist: matplotlib>=3.5.0; extra == "html"
Requires-Dist: seaborn>=0.11.0; extra == "html"
Requires-Dist: plotly>=5.0.0; extra == "html"
Dynamic: author
Dynamic: home-page
Dynamic: license-file
Dynamic: requires-python
